CHANGES.rst
MANIFEST.in
README.rst
TODO.rst
setup.py
djangobars/__init__.py
djangobars/settings.py
djangobars/shortcuts.py
djangobars.egg-info/PKG-INFO
djangobars.egg-info/SOURCES.txt
djangobars.egg-info/dependency_links.txt
djangobars.egg-info/requires.txt
djangobars.egg-info/top_level.txt
djangobars/template/__init__.py
djangobars/template/base.py
djangobars/template/helpers.py
djangobars/template/loader.py
djangobars/template/response.py
djangobars/template/loaders/__init__.py
djangobars/template/loaders/app_directories.py
djangobars/template/loaders/filesystem.py
djangobars/templatetags/__init__.py
djangobars/templatetags/djangobars.py