Metadata-Version: 1.1
Name: djangobars
Version: 0.2.1
Summary: An extension to allow Django to use Handlebars templates through the pybars port of Handlebars.js
Home-page: https://github.com/mjumbewu/djangobars/
Author: Mjumbe Wawatu Ukweli
Author-email: mjumbewu@gmail.com
License: UNKNOWN
Platform: UNKNOWN
Classifier: Development Status :: 3 - Alpha
Classifier: Environment :: Web Environment
Classifier: Intended Audience :: Developers
Classifier: License :: OSI Approved :: BSD License
Classifier: Operating System :: OS Independent
Classifier: Programming Language :: Python
Classifier: Programming Language :: Python :: 2
Classifier: Programming Language :: Python :: 2.7
Classifier: Programming Language :: Python :: 3
Classifier: Programming Language :: Python :: 3.3
Classifier: Framework :: Django
